[
    {"latitude": 17.385044, "longitude": 78.486671, "timestamp": "2024-07-20T10:00:00Z"},
    {"latitude": 17.385545, "longitude": 78.486872, "timestamp": "2024-07-20T10:00:05Z"},
    {"latitude": 17.386046, "longitude": 78.487073, "timestamp": "2024-07-20T10:00:10Z"},
    {"latitude": 17.386547, "longitude": 78.487274, "timestamp": "2024-07-20T10:00:15Z"},
    {"latitude": 17.387048, "longitude": 78.487475, "timestamp": "2024-07-20T10:00:20Z"},
    {"latitude": 17.387549, "longitude": 78.487676, "timestamp": "2024-07-20T10:00:25Z"},
    {"latitude": 17.388050, "longitude": 78.487877, "timestamp": "2024-07-20T10:00:30Z"},
    {"latitude": 17.388551, "longitude": 78.488078, "timestamp": "2024-07-20T10:00:35Z"},
    {"latitude": 17.389052, "longitude": 78.488279, "timestamp": "2024-07-20T10:00:40Z"},
    {"latitude": 17.389553, "longitude": 78.488480, "timestamp": "2024-07-20T10:00:45Z"}
  ]
  
  